ImageDownloader/__init__.py
ImageDownloader/image.py
ImageDownloader/image_downloader.py
ImageDownloader/image_group.py
ImageDownloader/images_page.py
ImageDownloader/inputs.py
Merkurial_ImageDownloader-0.0.2.dist-info/LICENSE
Merkurial_ImageDownloader-0.0.2.dist-info/METADATA
Merkurial_ImageDownloader-0.0.2.dist-info/WHEEL
Merkurial_ImageDownloader-0.0.2.dist-info/top_level.txt
Merkurial_ImageDownloader-0.0.2.dist-info/RECORD
