Metadata-Version: 2.1
Name: Merkurial-ImageDownloader
Version: 0.0.2
Summary: ImageDownloader Is A Very Easy Way To Automate The Downloading Of Images From A WebPage. There Is A Lot Of Flexibility
Author-email: Brandon Marcure <brandon@merkurialphoenix.com>
Project-URL: Homepage, https://github.com/ArisenPhoenix/ImageDownloader
Project-URL: Bug Tracker, https://github.com/ArisenPhoenix/ImageDownloader/issues
Classifier: Programming Language :: Python :: 3
Classifier: License :: OSI Approved :: GNU General Public License (GPL)
Classifier: Operating System :: OS Independent
Requires-Python: >=3.10
License-File: LICENSE
Requires-Dist: Merkurial-FileUtils >=0.0.0
